rxnplot/__init__.py
rxnplot/baseline.py
rxnplot/edge.py
rxnplot/energy.py
rxnplot/level.py
rxnplot/rxnlvl_util.py
rxnplot-0.9.2.dist-info/LICENSE
rxnplot-0.9.2.dist-info/METADATA
rxnplot-0.9.2.dist-info/WHEEL
rxnplot-0.9.2.dist-info/top_level.txt
rxnplot-0.9.2.dist-info/RECORD
