Metadata-Version: 2.1
Name: rxnplot
Version: 0.9.2
Summary: Tool to build energy diagrams of chemical reactions
Home-page: https://github.com/josemvas/rxnplot
License: LGPLv3+
Keywords: reaction plot jupyter
Platform: UNKNOWN
Classifier: Programming Language :: Python :: 3 :: Only
Classifier: License :: OSI Approved :: GNU Lesser General Public License v3 or later (LGPLv3+)
Classifier: Operating System :: POSIX
Requires-Python: >=3.3
Requires-Dist: IPython
Requires-Dist: cairosvg
